tcping.py
tcping-0.1.1rc1.data/scripts/tcping.py
tcping-0.1.1rc1.dist-info/DESCRIPTION.rst
tcping-0.1.1rc1.dist-info/METADATA
tcping-0.1.1rc1.dist-info/RECORD
tcping-0.1.1rc1.dist-info/WHEEL
tcping-0.1.1rc1.dist-info/entry_points.txt
tcping-0.1.1rc1.dist-info/metadata.json
tcping-0.1.1rc1.dist-info/top_level.txt
